amthyst_generator/__init__.py
amthyst_generator/files.yaml
amthyst_generator/main.py
amthyst_generator-1.1.1.dist-info/METADATA
amthyst_generator-1.1.1.dist-info/WHEEL
amthyst_generator-1.1.1.dist-info/entry_points.txt
amthyst_generator-1.1.1.dist-info/top_level.txt
amthyst_generator-1.1.1.dist-info/RECORD
