Metadata-Version: 2.2
Name: amthyst_generator
Version: 1.1.1
Requires-Dist: PyYAML~=6.0.2
Requires-Dist: questionary~=2.1.0
Dynamic: requires-dist
